{
  "updated": "2026-03-16T10:00:42.253134+08:00",
  "source": "SANPO Predictions - Polymarket",
  "count": 30,
  "markets": [
    {
      "question": "Democratic Presidential Nominee 2028",
      "subtitle": "",
      "outcomes": [
        {
          "label": "Gavin Newsom",
          "pct": 24.5
        },
        {
          "label": "Alexandria Ocasio-Cortez",
          "pct": 8.8
        },
        {
          "label": "Kamala Harris",
          "pct": 5.3
        }
      ],
      "volume": 831147555.6982976,
      "volume24": 6441723.652640998,
      "vol1wk": 46197491.91601699,
      "liquidity": 43054740.30959,
      "open_interest": 0.0,
      "category": "",
      "expiry": "07 Nov 2028",
      "url": "https://polymarket.com/event/democratic-presidential-nominee-2028"
    },
    {
      "question": "Fed decision in March?",
      "subtitle": "",
      "outcomes": [
        {
          "label": "No change",
          "pct": 99.6
        },
        {
          "label": "25 bps decrease",
          "pct": 0.4
        },
        {
          "label": "50+ bps decrease",
          "pct": 0.1
        }
      ],
      "volume": 421959823.2846241,
      "volume24": 22526486.778063003,
      "vol1wk": 139809990.47566783,
      "liquidity": 19325878.80721,
      "open_interest": 0.0,
      "category": "",
      "expiry": "18 Mar 2026",
      "url": "https://polymarket.com/event/fed-decision-in-march-885"
    },
    {
      "question": "Republican Presidential Nominee 2028",
      "subtitle": "",
      "outcomes": [
        {
          "label": "Robert F. Kennedy Jr.",
          "pct": 49.0
        },
        {
          "label": "J.D. Vance",
          "pct": 38.1
        },
        {
          "label": "Marco Rubio",
          "pct": 25.7
        }
      ],
      "volume": 418073688.56766397,
      "volume24": 5264727.2794429995,
      "vol1wk": 52207636.63991403,
      "liquidity": 21723298.75355,
      "open_interest": 0.0,
      "category": "",
      "expiry": "07 Nov 2028",
      "url": "https://polymarket.com/event/republican-presidential-nominee-2028"
    },
    {
      "question": "Presidential Election Winner 2028",
      "subtitle": "",
      "outcomes": [
        {
          "label": "JD Vance",
          "pct": 20.9
        },
        {
          "label": "Gavin Newsom",
          "pct": 18.1
        },
        {
          "label": "Marco Rubio",
          "pct": 13.8
        }
      ],
      "volume": 410317828.5914075,
      "volume24": 5410486.133001005,
      "vol1wk": 34352973.85801597,
      "liquidity": 25968911.5394,
      "open_interest": 0.0,
      "category": "",
      "expiry": "07 Nov 2028",
      "url": "https://polymarket.com/event/presidential-election-winner-2028"
    },
    {
      "question": "2026 FIFA World Cup Winner ",
      "subtitle": "",
      "outcomes": [
        {
          "label": "Spain",
          "pct": 15.4
        },
        {
          "label": "England",
          "pct": 13.2
        },
        {
          "label": "Argentina",
          "pct": 11.5
        }
      ],
      "volume": 307176779.57616395,
      "volume24": 7739400.132520906,
      "vol1wk": 32902046.000582933,
      "liquidity": 43162312.46648,
      "open_interest": 0.0,
      "category": "",
      "expiry": "20 Jul 2026",
      "url": "https://polymarket.com/event/2026-fifa-world-cup-winner-595"
    },
    {
      "question": "2026 NBA Champion",
      "subtitle": "",
      "outcomes": [
        {
          "label": "Oklahoma City Thunder",
          "pct": 35.5
        },
        {
          "label": "San Antonio Spurs",
          "pct": 13.8
        },
        {
          "label": "Boston Celtics",
          "pct": 13.0
        }
      ],
      "volume": 254631690.404208,
      "volume24": 4205683.308422,
      "vol1wk": 19850576.724613998,
      "liquidity": 14514483.72502,
      "open_interest": 0.0,
      "category": "",
      "expiry": "01 Jul 2026",
      "url": "https://polymarket.com/event/2026-nba-champion"
    },
    {
      "question": "The Masters - Winner ",
      "subtitle": "",
      "outcomes": [
        {
          "label": "Scottie Scheffler",
          "pct": 19.5
        },
        {
          "label": "Rory McIlroy",
          "pct": 9.0
        },
        {
          "label": "Jon Rahm",
          "pct": 5.8
        }
      ],
      "volume": 44465282.09266704,
      "volume24": 2146268.713222,
      "vol1wk": 15688559.286523001,
      "liquidity": 2190744.96887,
      "open_interest": 0.0,
      "category": "",
      "expiry": "13 Apr 2026",
      "url": "https://polymarket.com/event/the-masters-winner"
    },
    {
      "question": "What price will Bitcoin hit in March?",
      "subtitle": "",
      "outcomes": [
        {
          "label": "↑ 70,000",
          "pct": 100.0
        },
        {
          "label": "↑ 75,000",
          "pct": 74.5
        },
        {
          "label": "↓ 65,000",
          "pct": 34.2
        }
      ],
      "volume": 44001034.57782683,
      "volume24": 1662778.2346259994,
      "vol1wk": 21524625.922809012,
      "liquidity": 4539624.39688,
      "open_interest": 0.0,
      "category": "",
      "expiry": "01 Apr 2026",
      "url": "https://polymarket.com/event/what-price-will-bitcoin-hit-in-march-2026"
    },
    {
      "question": "Oscars 2026: Best Picture Winner",
      "subtitle": "",
      "outcomes": [
        {
          "label": "One Battle After Another",
          "pct": 76.5
        },
        {
          "label": "Sinners",
          "pct": 23.8
        },
        {
          "label": "The Secret Agent",
          "pct": 0.3
        }
      ],
      "volume": 38174551.16036887,
      "volume24": 4730160.477735,
      "vol1wk": 11873121.586724008,
      "liquidity": 636443.64146,
      "open_interest": 0.0,
      "category": "",
      "expiry": "15 Mar 2026",
      "url": "https://polymarket.com/event/oscars-2026-best-picture-winner"
    },
    {
      "question": "Will the Iranian regime fall by March 31?",
      "subtitle": "",
      "outcomes": [
        {
          "label": "No",
          "pct": 96.2
        },
        {
          "label": "Yes",
          "pct": 3.8
        }
      ],
      "volume": 34155869.43276289,
      "volume24": 1698118.7983290006,
      "vol1wk": 8486399.49598599,
      "liquidity": 1255486.00151,
      "open_interest": 0.0,
      "category": "",
      "expiry": "31 Mar 2026",
      "url": "https://polymarket.com/event/will-the-iranian-regime-fall-by-march-31"
    },
    {
      "question": "Will Crude Oil (CL) hit__ by end of March?",
      "subtitle": "",
      "outcomes": [
        {
          "label": "↑ $90",
          "pct": 100.0
        },
        {
          "label": "↑ $80",
          "pct": 100.0
        },
        {
          "label": "↑ $75",
          "pct": 100.0
        }
      ],
      "volume": 32187412.911930934,
      "volume24": 1994311.8328019995,
      "vol1wk": 21582625.545444075,
      "liquidity": 1408078.1273,
      "open_interest": 0.0,
      "category": "",
      "expiry": "31 Mar 2026",
      "url": "https://polymarket.com/event/will-crude-oil-cl-hit-by-end-of-march"
    },
    {
      "question": "US x Iran ceasefire by...?",
      "subtitle": "",
      "outcomes": [
        {
          "label": "December 31",
          "pct": 70.5
        },
        {
          "label": "June 30",
          "pct": 58.5
        },
        {
          "label": "May 31",
          "pct": 48.0
        }
      ],
      "volume": 29371696.443012256,
      "volume24": 2861177.319577001,
      "vol1wk": 19380462.634447988,
      "liquidity": 1493458.91641,
      "open_interest": 0.0,
      "category": "",
      "expiry": "",
      "url": "https://polymarket.com/event/us-x-iran-ceasefire-by"
    },
    {
      "question": "Netanyahu out by...?",
      "subtitle": "",
      "outcomes": [
        {
          "label": "December 31",
          "pct": 43.0
        },
        {
          "label": "June 30",
          "pct": 13.5
        },
        {
          "label": "March 31",
          "pct": 3.5
        }
      ],
      "volume": 17010907.392054062,
      "volume24": 10249748.96244402,
      "vol1wk": 16579575.463581176,
      "liquidity": 1631970.00919,
      "open_interest": 0.0,
      "category": "",
      "expiry": "31 Dec 2026",
      "url": "https://polymarket.com/event/netanyahu-out-before-2027"
    },
    {
      "question": "Iran strikes Israel on...?",
      "subtitle": "",
      "outcomes": [
        {
          "label": "March 4",
          "pct": 100.0
        },
        {
          "label": "March 1",
          "pct": 100.0
        },
        {
          "label": "March 2",
          "pct": 100.0
        }
      ],
      "volume": 12505793.848427016,
      "volume24": 2665580.4540230003,
      "vol1wk": 12430906.040128998,
      "liquidity": 1430139.27706,
      "open_interest": 0.0,
      "category": "",
      "expiry": "",
      "url": "https://polymarket.com/event/iran-strikes-israel-on"
    },
    {
      "question": "Oscars 2026: Best Actor Winner",
      "subtitle": "",
      "outcomes": [
        {
          "label": "Michael B. Jordan",
          "pct": 73.8
        },
        {
          "label": "Timothée Chalamet",
          "pct": 21.5
        },
        {
          "label": "Leonardo DiCaprio",
          "pct": 4.2
        }
      ],
      "volume": 12438501.167078974,
      "volume24": 3556791.271439,
      "vol1wk": 7007329.160557014,
      "liquidity": 131898.19132,
      "open_interest": 0.0,
      "category": "",
      "expiry": "15 Mar 2026",
      "url": "https://polymarket.com/event/oscars-2026-best-actor-winner"
    },
    {
      "question": "Hungary Parliamentary Election Winner",
      "subtitle": "",
      "outcomes": [
        {
          "label": "TISZA",
          "pct": 64.5
        },
        {
          "label": "Fidesz-KDNP",
          "pct": 35.5
        },
        {
          "label": "DK",
          "pct": 0.1
        }
      ],
      "volume": 10601061.352643995,
      "volume24": 4979287.290275001,
      "vol1wk": 9535788.163828993,
      "liquidity": 262859.14823,
      "open_interest": 0.0,
      "category": "",
      "expiry": "12 Apr 2026",
      "url": "https://polymarket.com/event/hungary-parliamentary-election-winner"
    },
    {
      "question": "Elon Musk # tweets March 10 - March 17, 2026?",
      "subtitle": "",
      "outcomes": [
        {
          "label": "280-299",
          "pct": 33.5
        },
        {
          "label": "300-319",
          "pct": 21.5
        },
        {
          "label": "260-279",
          "pct": 18.4
        }
      ],
      "volume": 9489618.236578003,
      "volume24": 3007766.005888999,
      "vol1wk": 8963230.223318001,
      "liquidity": 1736932.50142,
      "open_interest": 0.0,
      "category": "",
      "expiry": "17 Mar 2026",
      "url": "https://polymarket.com/event/elon-musk-of-tweets-march-10-march-17"
    },
    {
      "question": "Warriors vs. Knicks",
      "subtitle": "",
      "outcomes": [
        {
          "label": "Josh Hart: Assists O/U 4.5",
          "pct": 100.0
        },
        {
          "label": "Brandin Podziemski: Points O/U 18.5",
          "pct": 100.0
        },
        {
          "label": "1H Moneyline",
          "pct": 100.0
        }
      ],
      "volume": 7565480.581022953,
      "volume24": 7462586.806196994,
      "vol1wk": 7566078.659565993,
      "liquidity": 432582.20088,
      "open_interest": 0.0,
      "category": "",
      "expiry": "16 Mar 2026",
      "url": "https://polymarket.com/event/nba-gsw-nyk-2026-03-15"
    },
    {
      "question": "Iran leadership change by...?",
      "subtitle": "",
      "outcomes": [
        {
          "label": "December 31",
          "pct": 67.5
        },
        {
          "label": "April 30",
          "pct": 44.0
        },
        {
          "label": "March 31",
          "pct": 20.5
        }
      ],
      "volume": 6923972.866949004,
      "volume24": 1922441.2088280008,
      "vol1wk": 6924039.973948995,
      "liquidity": 969312.43668,
      "open_interest": 0.0,
      "category": "",
      "expiry": "31 Dec 2026",
      "url": "https://polymarket.com/event/iran-leadership-change-by"
    },
    {
      "question": "Pacers vs. Bucks",
      "subtitle": "",
      "outcomes": [
        {
          "label": "O/U 241.5",
          "pct": 100.0
        },
        {
          "label": "O/U 239.5",
          "pct": 100.0
        },
        {
          "label": "O/U 255.5",
          "pct": 100.0
        }
      ],
      "volume": 5353586.534886002,
      "volume24": 5315114.377117004,
      "vol1wk": 5353586.5348860035,
      "liquidity": 829634.96753,
      "open_interest": 0.0,
      "category": "",
      "expiry": "15 Mar 2026",
      "url": "https://polymarket.com/event/nba-ind-mil-2026-03-15"
    },
    {
      "question": "Trail Blazers vs. 76ers",
      "subtitle": "",
      "outcomes": [
        {
          "label": "Deni Avdija: Assists O/U 7.5",
          "pct": 100.0
        },
        {
          "label": "Spread -4.5",
          "pct": 100.0
        },
        {
          "label": "1H Moneyline",
          "pct": 100.0
        }
      ],
      "volume": 4779044.008932984,
      "volume24": 4733624.759757004,
      "vol1wk": 4779044.008933003,
      "liquidity": 3952158.92894,
      "open_interest": 0.0,
      "category": "",
      "expiry": "15 Mar 2026",
      "url": "https://polymarket.com/event/nba-por-phi-2026-03-15"
    },
    {
      "question": "Mavericks vs. Cavaliers",
      "subtitle": "",
      "outcomes": [
        {
          "label": "Mavericks vs. Cavaliers",
          "pct": 100.0
        },
        {
          "label": "O/U 241.5",
          "pct": 100.0
        },
        {
          "label": "Spread -8.5",
          "pct": 100.0
        }
      ],
      "volume": 4650323.963227019,
      "volume24": 4523433.757466992,
      "vol1wk": 4650323.96322699,
      "liquidity": 1054851.74714,
      "open_interest": 0.0,
      "category": "",
      "expiry": "15 Mar 2026",
      "url": "https://polymarket.com/event/nba-dal-cle-2026-03-15"
    },
    {
      "question": "Pistons vs. Raptors",
      "subtitle": "",
      "outcomes": [
        {
          "label": "O/U 223.5",
          "pct": 100.0
        },
        {
          "label": "Spread -2.5",
          "pct": 100.0
        },
        {
          "label": "Spread -4.5",
          "pct": 100.0
        }
      ],
      "volume": 4009643.7434209967,
      "volume24": 3961654.7003450003,
      "vol1wk": 4009643.7434210014,
      "liquidity": 1249553.75488,
      "open_interest": 0.0,
      "category": "",
      "expiry": "15 Mar 2026",
      "url": "https://polymarket.com/event/nba-det-tor-2026-03-15"
    },
    {
      "question": "Dota 2: Team Yandex vs Team Liquid (BO5) - PGL Wallachia Playoffs",
      "subtitle": "",
      "outcomes": [
        {
          "label": "Total Kills Over/Under 68.5 in Game 3?",
          "pct": 100.0
        },
        {
          "label": "Total Kills Over/Under 69.5 in Game 3?",
          "pct": 100.0
        },
        {
          "label": "Total Kills Over/Under 70.5 in Game 3?",
          "pct": 100.0
        }
      ],
      "volume": 3305024.4110399997,
      "volume24": 3305024.4110400006,
      "vol1wk": 3305024.4110400006,
      "liquidity": 69.2354,
      "open_interest": 0.0,
      "category": "",
      "expiry": "15 Mar 2026",
      "url": "https://polymarket.com/event/dota2-ty-liquid-2026-03-15"
    },
    {
      "question": "Jazz vs. Kings",
      "subtitle": "",
      "outcomes": [
        {
          "label": "Nique Clifford: Assists O/U 3.5",
          "pct": 77.0
        },
        {
          "label": "Nique Clifford: Assists O/U 5.5",
          "pct": 67.0
        },
        {
          "label": "Nique Clifford: Points O/U 14.5",
          "pct": 61.5
        }
      ],
      "volume": 3249988.481523011,
      "volume24": 3178247.825408998,
      "vol1wk": 3250987.837344998,
      "liquidity": 2234538.82102,
      "open_interest": 0.0,
      "category": "",
      "expiry": "16 Mar 2026",
      "url": "https://polymarket.com/event/nba-uta-sac-2026-03-15"
    },
    {
      "question": "Bitcoin above ___ on March 16?",
      "subtitle": "",
      "outcomes": [
        {
          "label": "60,000",
          "pct": 100.0
        },
        {
          "label": "62,000",
          "pct": 100.0
        },
        {
          "label": "58,000",
          "pct": 100.0
        }
      ],
      "volume": 2899392.751749,
      "volume24": 1602330.6106460001,
      "vol1wk": 2899392.7517489996,
      "liquidity": 403179.00822,
      "open_interest": 0.0,
      "category": "",
      "expiry": "16 Mar 2026",
      "url": "https://polymarket.com/event/bitcoin-above-on-march-16"
    },
    {
      "question": "Counter-Strike: Natus Vincere vs Aurora Gaming (BO5) - ESL Pro League Playoffs",
      "subtitle": "",
      "outcomes": [
        {
          "label": "Match Winner",
          "pct": 100.0
        },
        {
          "label": "Map 1 Winner",
          "pct": 100.0
        },
        {
          "label": "Map 3 Winner",
          "pct": 100.0
        }
      ],
      "volume": 2701581.8382809972,
      "volume24": 2690782.230533002,
      "vol1wk": 2701581.838281002,
      "liquidity": 86.15618,
      "open_interest": 0.0,
      "category": "",
      "expiry": "15 Mar 2026",
      "url": "https://polymarket.com/event/cs2-navi-aur1-2026-03-15"
    },
    {
      "question": "Dota 2: BetBoom Team vs Team Liquid (BO3) - PGL Wallachia Playoffs",
      "subtitle": "",
      "outcomes": [
        {
          "label": "Total Kills Over/Under 49.5 in Game 2?",
          "pct": 100.0
        },
        {
          "label": "Total Kills Over/Under 42.5 in Game 2?",
          "pct": 100.0
        },
        {
          "label": "Total Kills Over/Under 50.5 in Game 2?",
          "pct": 100.0
        }
      ],
      "volume": 2124020.9921490015,
      "volume24": 2112990.3474269984,
      "vol1wk": 2124020.9921489987,
      "liquidity": 203.89734,
      "open_interest": 0.0,
      "category": "",
      "expiry": "15 Mar 2026",
      "url": "https://polymarket.com/event/dota2-bb4-liquid-2026-03-15"
    },
    {
      "question": "Ducks vs. Canadiens",
      "subtitle": "",
      "outcomes": [
        {
          "label": "Ducks vs. Canadiens",
          "pct": 100.0
        },
        {
          "label": "O/U 4.5",
          "pct": 100.0
        },
        {
          "label": "O/U 5.5",
          "pct": 100.0
        }
      ],
      "volume": 1893574.2360320014,
      "volume24": 1881480.91633,
      "vol1wk": 1893524.5064699997,
      "liquidity": 1557866.10413,
      "open_interest": 0.0,
      "category": "",
      "expiry": "15 Mar 2026",
      "url": "https://polymarket.com/event/nhl-ana-mon-2026-03-15"
    },
    {
      "question": "BNP Paribas Open: Daniil Medvedev vs Jannik Sinner",
      "subtitle": "",
      "outcomes": [
        {
          "label": "BNP Paribas Open: Daniil Medvedev vs Jannik Sinner Set 1 O/U 8.5",
          "pct": 100.0
        },
        {
          "label": "BNP Paribas Open: Daniil Medvedev vs Jannik Sinner Set 1 O/U 9.5",
          "pct": 100.0
        },
        {
          "label": "BNP Paribas Open: Daniil Medvedev vs Jannik Sinner Set 1 O/U 10.5",
          "pct": 100.0
        }
      ],
      "volume": 1877049.5082180027,
      "volume24": 1877049.5082180025,
      "vol1wk": 1877049.5082180025,
      "liquidity": 2315994.32509,
      "open_interest": 0.0,
      "category": "",
      "expiry": "22 Mar 2026",
      "url": "https://polymarket.com/event/atp-medvede-sinner-2026-03-15"
    }
  ]
}