{
  "updated": "2026-05-01T08:30:08.137241+08:00",
  "source": "SANPO Predictions - Polymarket",
  "count": 30,
  "markets": [
    {
      "question": "Democratic Presidential Nominee 2028",
      "subtitle": "",
      "outcomes": [
        {
          "label": "Gavin Newsom",
          "pct": 27.0
        },
        {
          "label": "Kamala Harris",
          "pct": 9.3
        },
        {
          "label": "Alexandria Ocasio-Cortez",
          "pct": 8.5
        }
      ],
      "volume": 1119179666.6622632,
      "volume24": 2458051.1856629997,
      "vol1wk": 21794120.912279002,
      "liquidity": 48503092.76967,
      "open_interest": 12979256.471682,
      "category": "",
      "expiry": "07 Nov 2028",
      "url": "https://polymarket.com/event/democratic-presidential-nominee-2028"
    },
    {
      "question": "2026 FIFA World Cup Winner ",
      "subtitle": "",
      "outcomes": [
        {
          "label": "France",
          "pct": 16.4
        },
        {
          "label": "Spain",
          "pct": 15.2
        },
        {
          "label": "England",
          "pct": 11.1
        }
      ],
      "volume": 955859570.9225451,
      "volume24": 15494073.261239,
      "vol1wk": 215034691.00519195,
      "liquidity": 192045207.33943,
      "open_interest": 10546191.861350998,
      "category": "",
      "expiry": "20 Jul 2026",
      "url": "https://polymarket.com/event/2026-fifa-world-cup-winner-595"
    },
    {
      "question": "Republican Presidential Nominee 2028",
      "subtitle": "",
      "outcomes": [
        {
          "label": "Robert F. Kennedy Jr.",
          "pct": 49.0
        },
        {
          "label": "J.D. Vance",
          "pct": 38.6
        },
        {
          "label": "Marco Rubio",
          "pct": 21.3
        }
      ],
      "volume": 598545232.8781897,
      "volume24": 2806788.715514,
      "vol1wk": 19136104.190281,
      "liquidity": 17524099.88379,
      "open_interest": 9854006.342226,
      "category": "",
      "expiry": "07 Nov 2028",
      "url": "https://polymarket.com/event/republican-presidential-nominee-2028"
    },
    {
      "question": "Presidential Election Winner 2028",
      "subtitle": "",
      "outcomes": [
        {
          "label": "JD Vance",
          "pct": 21.6
        },
        {
          "label": "Gavin Newsom",
          "pct": 17.5
        },
        {
          "label": "Marco Rubio",
          "pct": 10.8
        }
      ],
      "volume": 564031025.6104118,
      "volume24": 2072961.071978,
      "vol1wk": 13381408.401802,
      "liquidity": 22509577.21797,
      "open_interest": 26363361.279937,
      "category": "",
      "expiry": "07 Nov 2028",
      "url": "https://polymarket.com/event/presidential-election-winner-2028"
    },
    {
      "question": "2026 NBA Champion",
      "subtitle": "",
      "outcomes": [
        {
          "label": "Oklahoma City Thunder",
          "pct": 51.5
        },
        {
          "label": "San Antonio Spurs",
          "pct": 17.5
        },
        {
          "label": "Boston Celtics",
          "pct": 12.0
        }
      ],
      "volume": 365146354.7914794,
      "volume24": 2858256.207535,
      "vol1wk": 43029111.001560956,
      "liquidity": 4519076.05467,
      "open_interest": 8476768.764050001,
      "category": "",
      "expiry": "01 Jul 2026",
      "url": "https://polymarket.com/event/2026-nba-champion"
    },
    {
      "question": "US x Iran ceasefire extended by...?",
      "subtitle": "",
      "outcomes": [
        {
          "label": "April 22",
          "pct": 0.1
        },
        {
          "label": "April 21",
          "pct": 0.0
        },
        {
          "label": "April 14",
          "pct": 0.0
        }
      ],
      "volume": 290290145.2521066,
      "volume24": 95862827.55007018,
      "vol1wk": 276313304.5260405,
      "liquidity": 2676759.86435,
      "open_interest": 141732872.096778,
      "category": "",
      "expiry": "22 Apr 2026",
      "url": "https://polymarket.com/event/us-x-iran-ceasefire-extended-by"
    },
    {
      "question": "Eurovision Winner 2026",
      "subtitle": "",
      "outcomes": [
        {
          "label": "Finland",
          "pct": 34.8
        },
        {
          "label": "Greece",
          "pct": 16.4
        },
        {
          "label": "Denmark",
          "pct": 12.6
        }
      ],
      "volume": 123778051.85282245,
      "volume24": 2827559.914669,
      "vol1wk": 15809700.498131998,
      "liquidity": 13904854.12658,
      "open_interest": 1589749.0037119999,
      "category": "",
      "expiry": "16 May 2026",
      "url": "https://polymarket.com/event/eurovision-winner-2026"
    },
    {
      "question": "US x Iran permanent peace deal by...?",
      "subtitle": "",
      "outcomes": [
        {
          "label": "June 30",
          "pct": 30.5
        },
        {
          "label": "May 31",
          "pct": 18.5
        },
        {
          "label": "May 15",
          "pct": 7.5
        }
      ],
      "volume": 71424320.20103726,
      "volume24": 3094629.1405580007,
      "vol1wk": 25018479.09512594,
      "liquidity": 1433193.90808,
      "open_interest": 7854126.598079001,
      "category": "",
      "expiry": "31 May 2026",
      "url": "https://polymarket.com/event/us-x-iran-permanent-peace-deal-by"
    },
    {
      "question": "What will WTI Crude Oil (WTI) hit in April 2026?",
      "subtitle": "",
      "outcomes": [
        {
          "label": "↑ $110",
          "pct": 100.0
        },
        {
          "label": "↑ $100",
          "pct": 100.0
        },
        {
          "label": "↑ $90",
          "pct": 100.0
        }
      ],
      "volume": 65453566.86330897,
      "volume24": 4386177.757587001,
      "vol1wk": 14959305.595966997,
      "liquidity": 2054842.59285,
      "open_interest": 7656708.302219999,
      "category": "",
      "expiry": "30 Apr 2026",
      "url": "https://polymarket.com/event/what-price-will-wti-hit-in-april-2026"
    },
    {
      "question": "What price will Bitcoin hit in April?",
      "subtitle": "",
      "outcomes": [
        {
          "label": "↑ 75,000",
          "pct": 100.0
        },
        {
          "label": "↑ 70,000",
          "pct": 100.0
        },
        {
          "label": "↓ 75,000",
          "pct": 100.0
        }
      ],
      "volume": 61764865.26626911,
      "volume24": 2056737.793505,
      "vol1wk": 19249920.957223974,
      "liquidity": 2768311.44216,
      "open_interest": 13023320.515088998,
      "category": "",
      "expiry": "01 May 2026",
      "url": "https://polymarket.com/event/what-price-will-bitcoin-hit-in-april-2026"
    },
    {
      "question": "Will the Iranian regime fall by April 30?",
      "subtitle": "",
      "outcomes": [
        {
          "label": "No",
          "pct": 100.0
        },
        {
          "label": "Yes",
          "pct": 0.1
        }
      ],
      "volume": 58424842.38266728,
      "volume24": 2568866.37,
      "vol1wk": 17712984.422089,
      "liquidity": 1590890.96504,
      "open_interest": 14901128.548593,
      "category": "",
      "expiry": "30 Apr 2026",
      "url": "https://polymarket.com/event/will-the-iranian-regime-fall-by-april-30"
    },
    {
      "question": "Next French Presidential Election",
      "subtitle": "",
      "outcomes": [
        {
          "label": "Jordan Bardella",
          "pct": 22.5
        },
        {
          "label": "Édouard Philippe",
          "pct": 21.5
        },
        {
          "label": "Jean-Luc Mélenchon",
          "pct": 8.5
        }
      ],
      "volume": 57027145.2994281,
      "volume24": 1614088.647691,
      "vol1wk": 6361403.137809,
      "liquidity": 4930118.09786,
      "open_interest": 477151.487307,
      "category": "",
      "expiry": "30 Apr 2027",
      "url": "https://polymarket.com/event/next-french-presidential-election"
    },
    {
      "question": "Kharg Island no longer under Iranian control by...?",
      "subtitle": "",
      "outcomes": [
        {
          "label": "June 30",
          "pct": 14.5
        },
        {
          "label": "May 31",
          "pct": 10.5
        },
        {
          "label": "April 30",
          "pct": 0.1
        }
      ],
      "volume": 40964416.90003067,
      "volume24": 1577823.818552,
      "vol1wk": 7268181.929955998,
      "liquidity": 781972.30044,
      "open_interest": 4870387.680458,
      "category": "",
      "expiry": "31 Mar 2026",
      "url": "https://polymarket.com/event/kharg-island-no-longer-under-iranian-control-by-march-31"
    },
    {
      "question": "Strait of Hormuz traffic returns to normal by end of April?",
      "subtitle": "",
      "outcomes": [
        {
          "label": "No",
          "pct": 99.9
        },
        {
          "label": "Yes",
          "pct": 0.1
        }
      ],
      "volume": 37041189.72155696,
      "volume24": 1808666.1225419997,
      "vol1wk": 11302862.266953975,
      "liquidity": 231971.45009,
      "open_interest": 4517353.17388,
      "category": "",
      "expiry": "30 Apr 2026",
      "url": "https://polymarket.com/event/strait-of-hormuz-traffic-returns-to-normal-by-april-30"
    },
    {
      "question": "US x Iran diplomatic meeting by...?",
      "subtitle": "",
      "outcomes": [
        {
          "label": "June 30",
          "pct": 60.5
        },
        {
          "label": "May 31",
          "pct": 39.5
        },
        {
          "label": "May 15",
          "pct": 23.5
        }
      ],
      "volume": 30231187.358227927,
      "volume24": 1413139.8581899996,
      "vol1wk": 9434336.727172006,
      "liquidity": 264942.39676,
      "open_interest": 1592733.4381890004,
      "category": "",
      "expiry": "30 Apr 2026",
      "url": "https://polymarket.com/event/us-x-iran-diplomatic-meeting-by-329"
    },
    {
      "question": "MegaETH market cap (FDV) one day after launch? ",
      "subtitle": "",
      "outcomes": [
        {
          "label": ">$800M",
          "pct": 100.0
        },
        {
          "label": ">$600M",
          "pct": 100.0
        },
        {
          "label": ">$1B",
          "pct": 99.5
        }
      ],
      "volume": 29314893.157705043,
      "volume24": 6125104.105893002,
      "vol1wk": 12012279.204804007,
      "liquidity": 956281.13639,
      "open_interest": 4166411.599468,
      "category": "",
      "expiry": "01 Jul 2026",
      "url": "https://polymarket.com/event/megaeth-market-cap-fdv-one-day-after-launch"
    },
    {
      "question": "Israel x Hezbollah Ceasefire extended by...?",
      "subtitle": "",
      "outcomes": [
        {
          "label": "April 26",
          "pct": 100.0
        },
        {
          "label": "April 21",
          "pct": 0.0
        }
      ],
      "volume": 27595169.37590522,
      "volume24": 14742609.809360983,
      "vol1wk": 26874015.482883103,
      "liquidity": 207603.09139,
      "open_interest": 14865812.481965002,
      "category": "",
      "expiry": "",
      "url": "https://polymarket.com/event/israel-x-hezbollah-ceasefire-extended-by"
    },
    {
      "question": "Tamil Nadu Legislative Assembly Election Winner",
      "subtitle": "",
      "outcomes": [
        {
          "label": "DMK",
          "pct": 84.5
        },
        {
          "label": "ADMK",
          "pct": 8.8
        },
        {
          "label": "TVK",
          "pct": 8.2
        }
      ],
      "volume": 23424890.450882737,
      "volume24": 6527204.389961015,
      "vol1wk": 22679483.439953737,
      "liquidity": 319659.44538,
      "open_interest": 455673.9640060001,
      "category": "",
      "expiry": "23 Apr 2026",
      "url": "https://polymarket.com/event/tamil-nadu-legislative-assembly-election-winner"
    },
    {
      "question": "Clavicular pregnancy in 2026?",
      "subtitle": "",
      "outcomes": [
        {
          "label": "Yes",
          "pct": 99.9
        },
        {
          "label": "No",
          "pct": 0.1
        }
      ],
      "volume": 20811359.488922082,
      "volume24": 8191223.446363002,
      "vol1wk": 20804193.016428147,
      "liquidity": 618444.70725,
      "open_interest": 5740405.559803,
      "category": "",
      "expiry": "31 Dec 2026",
      "url": "https://polymarket.com/event/clavicular-pregnancy-in-2026"
    },
    {
      "question": "When will Bitcoin hit $150k?",
      "subtitle": "",
      "outcomes": [
        {
          "label": "by December 31, 2026",
          "pct": 9.5
        },
        {
          "label": "by June 30, 2026",
          "pct": 1.4
        },
        {
          "label": "by September 30, 2025",
          "pct": 0.0
        }
      ],
      "volume": 18360481.244939998,
      "volume24": 5821943.554085,
      "vol1wk": 15545643.352421002,
      "liquidity": 49842.41715,
      "open_interest": 234416.104932,
      "category": "",
      "expiry": "",
      "url": "https://polymarket.com/event/when-will-bitcoin-hit-150k"
    },
    {
      "question": "Fed Decision in June?",
      "subtitle": "",
      "outcomes": [
        {
          "label": "No change",
          "pct": 95.5
        },
        {
          "label": "25 bps decrease",
          "pct": 3.5
        },
        {
          "label": "25 bps increase",
          "pct": 1.2
        }
      ],
      "volume": 17165913.110691946,
      "volume24": 2664820.1001709998,
      "vol1wk": 7164194.533546008,
      "liquidity": 1809192.05171,
      "open_interest": 1534471.791307,
      "category": "",
      "expiry": "17 Jun 2026",
      "url": "https://polymarket.com/event/fed-decision-in-june-825"
    },
    {
      "question": "Elon Musk # tweets April 24 - May 1, 2026?",
      "subtitle": "",
      "outcomes": [
        {
          "label": "180-199",
          "pct": 74.2
        },
        {
          "label": "200-219",
          "pct": 18.5
        },
        {
          "label": "160-179",
          "pct": 7.0
        }
      ],
      "volume": 11571475.368827006,
      "volume24": 4565515.112233998,
      "vol1wk": 10382055.858759003,
      "liquidity": 1311472.55309,
      "open_interest": 812672.9154780001,
      "category": "",
      "expiry": "01 May 2026",
      "url": "https://polymarket.com/event/elon-musk-of-tweets-april-24-may-1"
    },
    {
      "question": "Printr public sale total commitments?",
      "subtitle": "",
      "outcomes": [
        {
          "label": ">$250k",
          "pct": 100.0
        },
        {
          "label": ">$2M",
          "pct": 100.0
        },
        {
          "label": ">$500k",
          "pct": 100.0
        }
      ],
      "volume": 11035718.627011003,
      "volume24": 4962497.473596,
      "vol1wk": 10913919.851968003,
      "liquidity": 103744.28477,
      "open_interest": 1125308.146793,
      "category": "",
      "expiry": "01 Jun 2026",
      "url": "https://polymarket.com/event/printr-public-sale-total-commitments"
    },
    {
      "question": "Knicks vs. Hawks",
      "subtitle": "",
      "outcomes": [
        {
          "label": "CJ McCollum: Points O/U 4.5",
          "pct": 100.0
        },
        {
          "label": "Onyeka Okongwu: Rebounds O/U 1.5",
          "pct": 100.0
        },
        {
          "label": "OG Anunoby: Assists O/U 0.5",
          "pct": 100.0
        }
      ],
      "volume": 5056594.8151579825,
      "volume24": 5002938.222933001,
      "vol1wk": 5056594.815158002,
      "liquidity": 1298288.06531,
      "open_interest": 3433692.9432080006,
      "category": "",
      "expiry": "30 Apr 2026",
      "url": "https://polymarket.com/event/nba-nyk-atl-2026-04-30"
    },
    {
      "question": "Elon Musk # tweets April 28 - May 5, 2026?",
      "subtitle": "",
      "outcomes": [
        {
          "label": "160-179",
          "pct": 17.8
        },
        {
          "label": "140-159",
          "pct": 14.4
        },
        {
          "label": "180-199",
          "pct": 14.2
        }
      ],
      "volume": 4734942.232959998,
      "volume24": 2121789.554625,
      "vol1wk": 4260172.494422,
      "liquidity": 1131139.30342,
      "open_interest": 356536.52630300005,
      "category": "",
      "expiry": "05 May 2026",
      "url": "https://polymarket.com/event/elon-musk-of-tweets-april-28-may-5"
    },
    {
      "question": "Nuggets vs. Timberwolves",
      "subtitle": "",
      "outcomes": [
        {
          "label": "Julius Randle: Points O/U 4.5",
          "pct": 98.9
        },
        {
          "label": "Julius Randle: Rebounds O/U 1.5",
          "pct": 96.5
        },
        {
          "label": "Julius Randle: Assists O/U 0.5",
          "pct": 96.2
        }
      ],
      "volume": 4028640.3388539986,
      "volume24": 3888113.04988,
      "vol1wk": 4028188.347720001,
      "liquidity": 1606249.75732,
      "open_interest": 2251521.3877359997,
      "category": "",
      "expiry": "30 Apr 2026",
      "url": "https://polymarket.com/event/nba-den-min-2026-04-30"
    },
    {
      "question": "Celtics vs. 76ers",
      "subtitle": "",
      "outcomes": [
        {
          "label": "Sam Hauser: Points O/U 0.5",
          "pct": 99.5
        },
        {
          "label": "Neemias Queta: Rebounds O/U 1.5",
          "pct": 99.5
        },
        {
          "label": "Kelly Oubre Jr.: Rebounds O/U 1.5",
          "pct": 76.0
        }
      ],
      "volume": 3190280.251612002,
      "volume24": 3153903.9186560004,
      "vol1wk": 3190280.251612,
      "liquidity": 302784.96702,
      "open_interest": 1687718.3821210002,
      "category": "",
      "expiry": "30 Apr 2026",
      "url": "https://polymarket.com/event/nba-bos-phi-2026-04-30"
    },
    {
      "question": "Counter-Strike: FaZe vs FURIA (BO3) - BLAST Rivals Group B",
      "subtitle": "",
      "outcomes": [
        {
          "label": "Match Winner",
          "pct": 100.0
        },
        {
          "label": "Map 1 Winner",
          "pct": 100.0
        },
        {
          "label": "O/U 2.5 Games",
          "pct": 100.0
        }
      ],
      "volume": 2712773.947564001,
      "volume24": 2712773.947564002,
      "vol1wk": 2712773.947564002,
      "liquidity": 1378342.37473,
      "open_interest": 1665324.454379,
      "category": "",
      "expiry": "01 May 2026",
      "url": "https://polymarket.com/event/cs2-faze-furia-2026-04-30"
    },
    {
      "question": "What will WTI Crude Oil (WTI) hit in May 2026?",
      "subtitle": "",
      "outcomes": [
        {
          "label": "↑ $90",
          "pct": 99.9
        },
        {
          "label": "↑ $100",
          "pct": 99.7
        },
        {
          "label": "↑ $110",
          "pct": 82.0
        }
      ],
      "volume": 1980568.5042099997,
      "volume24": 1464383.2522989996,
      "vol1wk": 1980568.5042099997,
      "liquidity": 459920.99826,
      "open_interest": 783376.1619579999,
      "category": "",
      "expiry": "01 Jun 2026",
      "url": "https://polymarket.com/event/what-price-will-wti-hit-in-may-2026"
    },
    {
      "question": "Stars vs. Wild",
      "subtitle": "",
      "outcomes": [
        {
          "label": "O/U 4.5",
          "pct": 68.5
        },
        {
          "label": "Spread -1.5",
          "pct": 45.5
        },
        {
          "label": "O/U 5.5",
          "pct": 39.5
        }
      ],
      "volume": 1527536.8112679936,
      "volume24": 1526813.7112680003,
      "vol1wk": 1527536.8112680004,
      "liquidity": 297426.0414,
      "open_interest": 1399053.9991070002,
      "category": "",
      "expiry": "30 Apr 2026",
      "url": "https://polymarket.com/event/nhl-dal-min-2026-04-30"
    }
  ]
}