{
  "updated": "2026-06-13T23:00:08.356287+08:00",
  "source": "SANPO Predictions - Polymarket",
  "count": 30,
  "markets": [
    {
      "question": "World Cup Winner ",
      "subtitle": "",
      "outcomes": [
        {
          "label": "Spain",
          "pct": 16.8
        },
        {
          "label": "France",
          "pct": 16.1
        },
        {
          "label": "Portugal",
          "pct": 10.5
        }
      ],
      "volume": 2194271521.427007,
      "volume24": 70769035.61610895,
      "vol1wk": 569448774.0393318,
      "liquidity": 465797104.89518,
      "open_interest": 33391379.621863995,
      "category": "",
      "expiry": "20 Jul 2026",
      "url": "https://polymarket.com/event/world-cup-winner"
    },
    {
      "question": "Democratic Presidential Nominee 2028",
      "subtitle": "",
      "outcomes": [
        {
          "label": "Gavin Newsom",
          "pct": 23.2
        },
        {
          "label": "Jon Ossoff",
          "pct": 9.1
        },
        {
          "label": "Alexandria Ocasio-Cortez",
          "pct": 8.8
        }
      ],
      "volume": 1194702523.8472984,
      "volume24": 990860.724823,
      "vol1wk": 8660927.258895999,
      "liquidity": 65168661.00817,
      "open_interest": 11793980.829693997,
      "category": "",
      "expiry": "07 Nov 2028",
      "url": "https://polymarket.com/event/democratic-presidential-nominee-2028"
    },
    {
      "question": "Presidential Election Winner 2028",
      "subtitle": "",
      "outcomes": [
        {
          "label": "JD Vance",
          "pct": 15.2
        },
        {
          "label": "Marco Rubio",
          "pct": 14.5
        },
        {
          "label": "Gavin Newsom",
          "pct": 14.2
        }
      ],
      "volume": 626495680.8911384,
      "volume24": 953096.3397020001,
      "vol1wk": 8394564.381679995,
      "liquidity": 35705974.18711,
      "open_interest": 56863935.36381401,
      "category": "",
      "expiry": "07 Nov 2028",
      "url": "https://polymarket.com/event/presidential-election-winner-2028"
    },
    {
      "question": "2026 NBA Champion",
      "subtitle": "",
      "outcomes": [
        {
          "label": "New York Knicks",
          "pct": 80.6
        },
        {
          "label": "San Antonio Spurs",
          "pct": 19.7
        },
        {
          "label": "Oklahoma City Thunder",
          "pct": 0.0
        }
      ],
      "volume": 423648861.8129231,
      "volume24": 1317116.7747839997,
      "vol1wk": 10186887.05004502,
      "liquidity": 587752.571,
      "open_interest": 10036963.773582004,
      "category": "",
      "expiry": "01 Jul 2026",
      "url": "https://polymarket.com/event/2026-nba-champion"
    },
    {
      "question": "US x Iran permanent peace deal by...?",
      "subtitle": "",
      "outcomes": [
        {
          "label": "December 31",
          "pct": 83.5
        },
        {
          "label": "October 31",
          "pct": 77.5
        },
        {
          "label": "August 31",
          "pct": 70.5
        }
      ],
      "volume": 303504023.97631794,
      "volume24": 7827491.024713008,
      "vol1wk": 40179364.22454105,
      "liquidity": 1793156.18928,
      "open_interest": 18620632.852096997,
      "category": "",
      "expiry": "31 Dec 2026",
      "url": "https://polymarket.com/event/us-x-iran-permanent-peace-deal-by"
    },
    {
      "question": "F1 Drivers' Champion",
      "subtitle": "",
      "outcomes": [
        {
          "label": "Kimi Antonelli",
          "pct": 66.0
        },
        {
          "label": "George Russell",
          "pct": 21.5
        },
        {
          "label": "Lewis Hamilton",
          "pct": 2.9
        }
      ],
      "volume": 172225796.78927752,
      "volume24": 799401.416678,
      "vol1wk": 5531589.63905,
      "liquidity": 12874524.02063,
      "open_interest": 1266193.4774459999,
      "category": "",
      "expiry": "06 Dec 2026",
      "url": "https://polymarket.com/event/2026-f1-drivers-champion"
    },
    {
      "question": "Peru Presidential Election Winner",
      "subtitle": "",
      "outcomes": [
        {
          "label": "Keiko Fujimori",
          "pct": 98.3
        },
        {
          "label": "Roberto Sánchez Palomino",
          "pct": 1.3
        },
        {
          "label": "Rafael López Aliaga",
          "pct": 0.1
        }
      ],
      "volume": 100453029.84949164,
      "volume24": 956566.2447529997,
      "vol1wk": 35020388.098702244,
      "liquidity": 15545093.6862,
      "open_interest": 7969176.575637001,
      "category": "",
      "expiry": "12 Apr 2026",
      "url": "https://polymarket.com/event/peru-presidential-election-winner"
    },
    {
      "question": "Next French Presidential Election",
      "subtitle": "",
      "outcomes": [
        {
          "label": "Jordan Bardella",
          "pct": 26.5
        },
        {
          "label": "Édouard Philippe",
          "pct": 20.5
        },
        {
          "label": "Jean-Luc Mélenchon",
          "pct": 12.5
        }
      ],
      "volume": 98551269.2608172,
      "volume24": 1055735.507462,
      "vol1wk": 5778698.522903999,
      "liquidity": 9957974.9434,
      "open_interest": 676036.190699,
      "category": "",
      "expiry": "30 Apr 2027",
      "url": "https://polymarket.com/event/next-french-presidential-election"
    },
    {
      "question": "Fed Decision in June?",
      "subtitle": "",
      "outcomes": [
        {
          "label": "No change",
          "pct": 99.5
        },
        {
          "label": "25 bps decrease",
          "pct": 0.2
        },
        {
          "label": "25 bps increase",
          "pct": 0.2
        }
      ],
      "volume": 91244505.86362273,
      "volume24": 4333413.856757999,
      "vol1wk": 27629497.596978042,
      "liquidity": 8133163.7315,
      "open_interest": 13725567.642653001,
      "category": "",
      "expiry": "17 Jun 2026",
      "url": "https://polymarket.com/event/fed-decision-in-june-825"
    },
    {
      "question": "Will the Iranian regime fall by June 30?",
      "subtitle": "",
      "outcomes": [
        {
          "label": "No",
          "pct": 99.3
        },
        {
          "label": "Yes",
          "pct": 0.7
        }
      ],
      "volume": 54503703.12635521,
      "volume24": 1382025.6546270014,
      "vol1wk": 5589380.387028015,
      "liquidity": 780105.7274,
      "open_interest": 10998146.395728,
      "category": "",
      "expiry": "30 Jun 2026",
      "url": "https://polymarket.com/event/will-the-iranian-regime-fall-by-june-30"
    },
    {
      "question": "US announces new Iran agreement/ceasefire extension by...?",
      "subtitle": "",
      "outcomes": [
        {
          "label": "July 31",
          "pct": 85.0
        },
        {
          "label": "June 30",
          "pct": 80.5
        },
        {
          "label": "June 19",
          "pct": 77.0
        }
      ],
      "volume": 45844078.12748473,
      "volume24": 4941065.746761999,
      "vol1wk": 12896526.942615015,
      "liquidity": 866713.92799,
      "open_interest": 3463605.3850209997,
      "category": "",
      "expiry": "",
      "url": "https://polymarket.com/event/us-announces-new-iran-agreementceasefire-extension-by"
    },
    {
      "question": "Trump announces US blockade of Hormuz lifted by...?",
      "subtitle": "",
      "outcomes": [
        {
          "label": "July 31",
          "pct": 80.0
        },
        {
          "label": "June 30",
          "pct": 72.5
        },
        {
          "label": "June 15",
          "pct": 34.0
        }
      ],
      "volume": 32506551.132310882,
      "volume24": 845323.4292189999,
      "vol1wk": 3073167.1421350045,
      "liquidity": 232923.4445,
      "open_interest": 1142812.612021,
      "category": "",
      "expiry": "30 Jun 2026",
      "url": "https://polymarket.com/event/trump-announces-us-blockade-of-hormuz-lifted-by"
    },
    {
      "question": "Strait of Hormuz traffic returns to normal by end of June?",
      "subtitle": "",
      "outcomes": [
        {
          "label": "No",
          "pct": 78.5
        },
        {
          "label": "Yes",
          "pct": 21.5
        }
      ],
      "volume": 19823165.55508625,
      "volume24": 798668.4199529999,
      "vol1wk": 5678538.880805057,
      "liquidity": 539647.5406,
      "open_interest": 4570750.075286,
      "category": "",
      "expiry": "30 Jun 2026",
      "url": "https://polymarket.com/event/strait-of-hormuz-traffic-returns-to-normal-by-end-of-june"
    },
    {
      "question": "IEM Cologne Major 2026 Winner",
      "subtitle": "",
      "outcomes": [
        {
          "label": "Vitality",
          "pct": 40.5
        },
        {
          "label": "Team Spirit",
          "pct": 35.5
        },
        {
          "label": "FURIA",
          "pct": 8.0
        }
      ],
      "volume": 19077072.927851923,
      "volume24": 1182945.264052,
      "vol1wk": 7226331.344523004,
      "liquidity": 1403971.29923,
      "open_interest": 903314.0204950001,
      "category": "",
      "expiry": "21 Jun 2026",
      "url": "https://polymarket.com/event/iem-cologne-major-2026-winner"
    },
    {
      "question": "LoL: Team WE vs Bilibili Gaming (BO5) - LPL Playoffs",
      "subtitle": "",
      "outcomes": [
        {
          "label": "First Blood in Game 2?",
          "pct": 100.0
        },
        {
          "label": "First Blood in Game 3?",
          "pct": 100.0
        },
        {
          "label": "Total Kills Over/Under 30.5 in Game 2?",
          "pct": 100.0
        }
      ],
      "volume": 6835072.253469999,
      "volume24": 6722685.718535004,
      "vol1wk": 6835068.7918390045,
      "liquidity": 2234677.52192,
      "open_interest": 2365829.7107659993,
      "category": "",
      "expiry": "13 Jun 2026",
      "url": "https://polymarket.com/event/lol-we-blg-2026-06-13"
    },
    {
      "question": "Where will Maxx Crosby play in 2026?",
      "subtitle": "",
      "outcomes": [
        {
          "label": "Las Vegas Raiders",
          "pct": 75.6
        },
        {
          "label": "Seattle Seahawks",
          "pct": 9.0
        },
        {
          "label": "Philadelphia Eagles",
          "pct": 5.3
        }
      ],
      "volume": 6308714.866075001,
      "volume24": 1060930.1044629996,
      "vol1wk": 3710937.6898500007,
      "liquidity": 38113.1552,
      "open_interest": 10741.748086,
      "category": "",
      "expiry": "01 Sep 2026",
      "url": "https://polymarket.com/event/where-will-maxx-crosby-play-in-2026"
    },
    {
      "question": "Qatar vs. Switzerland - More Markets",
      "subtitle": "",
      "outcomes": [
        {
          "label": "O/U 0.5",
          "pct": 95.8
        },
        {
          "label": "Switzerland O/U 0.5",
          "pct": 93.0
        },
        {
          "label": "2nd Half O/U 0.5",
          "pct": 83.0
        }
      ],
      "volume": 5488012.436225987,
      "volume24": 4416068.685029003,
      "vol1wk": 5477117.876529002,
      "liquidity": 3765255.20357,
      "open_interest": 4572556.208718999,
      "category": "",
      "expiry": "13 Jun 2026",
      "url": "https://polymarket.com/event/fifwc-qat-che-2026-06-13-more-markets"
    },
    {
      "question": "Brazil vs. Morocco",
      "subtitle": "",
      "outcomes": [
        {
          "label": "Brazil",
          "pct": 58.5
        },
        {
          "label": "Draw (Brazil vs. Morocco)",
          "pct": 25.5
        },
        {
          "label": "Morocco",
          "pct": 16.5
        }
      ],
      "volume": 3774743.5643720487,
      "volume24": 2878918.0252500162,
      "vol1wk": 3656606.812110049,
      "liquidity": 8478642.4704,
      "open_interest": 2894673.574171,
      "category": "",
      "expiry": "13 Jun 2026",
      "url": "https://polymarket.com/event/fifwc-bra-mar-2026-06-13"
    },
    {
      "question": "Qatar vs. Switzerland",
      "subtitle": "",
      "outcomes": [
        {
          "label": "Switzerland",
          "pct": 81.5
        },
        {
          "label": "Draw (Qatar vs. Switzerland)",
          "pct": 13.5
        },
        {
          "label": "Qatar",
          "pct": 5.9
        }
      ],
      "volume": 3691953.5632950463,
      "volume24": 2459455.862574998,
      "vol1wk": 3615227.065292038,
      "liquidity": 8439227.66098,
      "open_interest": 2667003.05746,
      "category": "",
      "expiry": "13 Jun 2026",
      "url": "https://polymarket.com/event/fifwc-qat-che-2026-06-13"
    },
    {
      "question": "Knicks vs. Spurs",
      "subtitle": "",
      "outcomes": [
        {
          "label": "Devin Vassell: Points O/U 3.5",
          "pct": 96.2
        },
        {
          "label": "Julian Champagnie: Points O/U 2.5",
          "pct": 95.4
        },
        {
          "label": "Julian Champagnie: Rebounds O/U 1.5",
          "pct": 93.0
        }
      ],
      "volume": 3158440.9196740272,
      "volume24": 1395288.406419998,
      "vol1wk": 3158198.2465010197,
      "liquidity": 6283138.10791,
      "open_interest": 2718484.0561149996,
      "category": "",
      "expiry": "14 Jun 2026",
      "url": "https://polymarket.com/event/nba-nyk-sas-2026-06-13"
    },
    {
      "question": "Counter-Strike: Team Falcons vs Monte (BO3) - IEM Cologne Major Stage 3",
      "subtitle": "",
      "outcomes": [
        {
          "label": "Map 1 Winner",
          "pct": 100.0
        },
        {
          "label": "O/U 2.5 Games",
          "pct": 100.0
        },
        {
          "label": "Map 1 Rounds Handicap: Team Falcons (-3.5) vs Monte (+3.5)",
          "pct": 100.0
        }
      ],
      "volume": 2315604.784268,
      "volume24": 2315604.7842679988,
      "vol1wk": 2315604.7842679988,
      "liquidity": 837130.70153,
      "open_interest": 2063018.0067569998,
      "category": "",
      "expiry": "13 Jun 2026",
      "url": "https://polymarket.com/event/cs2-fal2-mnte-2026-06-13"
    },
    {
      "question": "Germany vs. Curaçao",
      "subtitle": "",
      "outcomes": [
        {
          "label": "Germany",
          "pct": 93.8
        },
        {
          "label": "Draw (Germany vs. Curaçao)",
          "pct": 4.0
        },
        {
          "label": "Curaçao",
          "pct": 2.5
        }
      ],
      "volume": 2174860.6737070037,
      "volume24": 875616.7676050004,
      "vol1wk": 1935162.8632640042,
      "liquidity": 1283038.45601,
      "open_interest": 921365.267615,
      "category": "",
      "expiry": "14 Jun 2026",
      "url": "https://polymarket.com/event/fifwc-ger-kor-2026-06-14"
    },
    {
      "question": "Counter-Strike: Aurora Gaming vs G2 (BO3) - IEM Cologne Major Stage 3",
      "subtitle": "",
      "outcomes": [
        {
          "label": "Map 1 Winner",
          "pct": 100.0
        },
        {
          "label": "Map 2 Winner",
          "pct": 100.0
        },
        {
          "label": "Match Winner",
          "pct": 100.0
        }
      ],
      "volume": 2025482.8927790006,
      "volume24": 2025482.892779,
      "vol1wk": 2025482.892779,
      "liquidity": 2327676.11302,
      "open_interest": 1304519.7099259999,
      "category": "",
      "expiry": "13 Jun 2026",
      "url": "https://polymarket.com/event/cs2-aur1-g2-2026-06-13"
    },
    {
      "question": "Brazil vs. Morocco - More Markets",
      "subtitle": "",
      "outcomes": [
        {
          "label": "O/U 0.5",
          "pct": 91.5
        },
        {
          "label": "Brazil O/U 0.5",
          "pct": 82.0
        },
        {
          "label": "2nd Half O/U 0.5",
          "pct": 75.0
        }
      ],
      "volume": 1925726.218577,
      "volume24": 1583456.6203809995,
      "vol1wk": 1919685.995563998,
      "liquidity": 1887364.05476,
      "open_interest": 1422431.489898999,
      "category": "",
      "expiry": "13 Jun 2026",
      "url": "https://polymarket.com/event/fifwc-bra-mar-2026-06-13-more-markets"
    },
    {
      "question": "Bitcoin above ___ on June 13?",
      "subtitle": "",
      "outcomes": [
        {
          "label": "50,000",
          "pct": 100.0
        },
        {
          "label": "52,000",
          "pct": 100.0
        },
        {
          "label": "54,000",
          "pct": 100.0
        }
      ],
      "volume": 1793220.1751080002,
      "volume24": 1190714.639111,
      "vol1wk": 1793220.1751079997,
      "liquidity": 847945.15483,
      "open_interest": 878937.1969049999,
      "category": "",
      "expiry": "13 Jun 2026",
      "url": "https://polymarket.com/event/bitcoin-above-on-june-13-2026"
    },
    {
      "question": "Haiti vs. Scotland",
      "subtitle": "",
      "outcomes": [
        {
          "label": "Scotland",
          "pct": 63.5
        },
        {
          "label": "Draw (Haiti vs. Scotland)",
          "pct": 21.5
        },
        {
          "label": "Haiti",
          "pct": 15.5
        }
      ],
      "volume": 1458549.5532590142,
      "volume24": 1058721.8593810012,
      "vol1wk": 1364183.520750997,
      "liquidity": 4908771.4452,
      "open_interest": 1204845.145202,
      "category": "",
      "expiry": "14 Jun 2026",
      "url": "https://polymarket.com/event/fifwc-hai-sco-2026-06-13"
    },
    {
      "question": "Australia vs. Türkiye",
      "subtitle": "",
      "outcomes": [
        {
          "label": "Türkiye",
          "pct": 57.5
        },
        {
          "label": "Draw (Australia vs. Türkiye)",
          "pct": 25.5
        },
        {
          "label": "Australia",
          "pct": 17.5
        }
      ],
      "volume": 1235291.2449289933,
      "volume24": 1025938.0942820034,
      "vol1wk": 1203964.1217230046,
      "liquidity": 2755775.5183,
      "open_interest": 1023961.46575,
      "category": "",
      "expiry": "14 Jun 2026",
      "url": "https://polymarket.com/event/fifwc-aus-tur-2026-06-14"
    },
    {
      "question": "Next Prime Minister of Ethiopia?",
      "subtitle": "",
      "outcomes": [
        {
          "label": "Abiy Ahmed",
          "pct": 98.8
        },
        {
          "label": "Adanech Abiebie",
          "pct": 0.9
        },
        {
          "label": "Shimelis Abdisa",
          "pct": 0.7
        }
      ],
      "volume": 1232361.148968,
      "volume24": 1204416.576,
      "vol1wk": 1210709.712573,
      "liquidity": 39560.86195,
      "open_interest": 5072.236942,
      "category": "",
      "expiry": "01 Jun 2026",
      "url": "https://polymarket.com/event/next-prime-minister-of-ethiopia"
    },
    {
      "question": "Elon Musk # tweets June 11 - June 13, 2026?",
      "subtitle": "",
      "outcomes": [
        {
          "label": "65-89",
          "pct": 72.5
        },
        {
          "label": "40-64",
          "pct": 39.9
        },
        {
          "label": "90-114",
          "pct": 0.4
        }
      ],
      "volume": 1205398.6070259998,
      "volume24": 785197.777682,
      "vol1wk": 1205398.6070259998,
      "liquidity": 216938.03064,
      "open_interest": 314103.81721000007,
      "category": "",
      "expiry": "13 Jun 2026",
      "url": "https://polymarket.com/event/elon-musk-of-tweets-june-11-june-13"
    },
    {
      "question": "Counter-Strike: Vitality vs MOUZ (BO3) - IEM Cologne Major Stage 3",
      "subtitle": "",
      "outcomes": [
        {
          "label": "Map 1 Winner",
          "pct": 87.0
        },
        {
          "label": "Match Winner",
          "pct": 86.5
        },
        {
          "label": "Map 2 Winner",
          "pct": 74.5
        }
      ],
      "volume": 773275.4103680002,
      "volume24": 773275.4103679996,
      "vol1wk": 773275.4103679996,
      "liquidity": 792381.0238,
      "open_interest": 982082.895993,
      "category": "",
      "expiry": "13 Jun 2026",
      "url": "https://polymarket.com/event/cs2-vit-mouz-2026-06-13"
    }
  ]
}